ensembl/utils/__init__.py
ensembl/utils/archive.py
ensembl/utils/argparse.py
ensembl/utils/checksums.py
ensembl/utils/logging.py
ensembl/utils/plugin.py
ensembl/utils/rloader.py
ensembl/utils/database/__init__.py
ensembl/utils/database/dbconnection.py
ensembl/utils/database/unittestdb.py
ensembl_utils-0.8.0.dist-info/licenses/LICENSE
ensembl_utils-0.8.0.dist-info/licenses/NOTICE
ensembl_utils-0.8.0.dist-info/METADATA
ensembl_utils-0.8.0.dist-info/WHEEL
ensembl_utils-0.8.0.dist-info/entry_points.txt
ensembl_utils-0.8.0.dist-info/top_level.txt
ensembl_utils-0.8.0.dist-info/RECORD
