Metadata-Version: 2.4
Name: ensembl-utils
Version: 0.8.0
Summary: Ensembl Python general-purpose utils
Author-email: Ensembl <dev@ensembl.org>
License-Expression: Apache-2.0
Project-URL: Homepage, https://www.ensembl.org
Project-URL: Documentation, https://ensembl.github.io/ensembl-utils/
Project-URL: Repository, https://github.com/Ensembl/ensembl-utils.git
Project-URL: Issues, https://github.com/Ensembl/ensembl-utils/issues
Keywords: ensembl,python,utils
Classifier: Development Status :: 4 - Beta
Classifier: Environment :: Console
Classifier: Framework :: Pytest
Classifier: Intended Audience :: Science/Research
Classifier: Operating System :: OS Independent
Classifier: Programming Language :: Python
Classifier: Programming Language :: Python :: 3
Classifier: Programming Language :: Python :: 3 :: Only
Classifier: Programming Language :: Python :: 3.10
Classifier: Programming Language :: Python :: 3.11
Classifier: Topic :: Scientific/Engineering :: Bio-Informatics
Classifier: Topic :: Software Development :: Libraries :: Python Modules
Requires-Python: >=3.10
License-File: LICENSE
License-File: NOTICE
Requires-Dist: pytest>=8.2.0
Requires-Dist: python-dotenv>=0.19.2
Requires-Dist: pyyaml~=6.0
Requires-Dist: requests>=2.22.0
Requires-Dist: sqlalchemy>=1.4.45
Requires-Dist: sqlalchemy_utils>=0.41.2
Provides-Extra: build
Requires-Dist: build; extra == "build"
Requires-Dist: setuptools; extra == "build"
Requires-Dist: setuptools-scm; extra == "build"
Requires-Dist: wheel; extra == "build"
Provides-Extra: cicd
Requires-Dist: black; extra == "cicd"
Requires-Dist: coverage; extra == "cicd"
Requires-Dist: genbadge[coverage]; extra == "cicd"
Requires-Dist: mypy; extra == "cicd"
Requires-Dist: pylint; extra == "cicd"
Requires-Dist: pytest-dependency; extra == "cicd"
Requires-Dist: types-pyyaml; extra == "cicd"
Requires-Dist: types-requests; extra == "cicd"
Provides-Extra: docs
Requires-Dist: mkdocs>=1.5.3; extra == "docs"
Requires-Dist: mkdocs-autorefs; extra == "docs"
Requires-Dist: mkdocs-coverage; extra == "docs"
Requires-Dist: mkdocs-gen-files; extra == "docs"
Requires-Dist: mkdocs-literate-nav; extra == "docs"
Requires-Dist: mkdocs-material; extra == "docs"
Requires-Dist: mkdocs-material-extensions; extra == "docs"
Requires-Dist: mkdocs-section-index; extra == "docs"
Requires-Dist: mkdocstrings; extra == "docs"
Requires-Dist: mkdocstrings-python; extra == "docs"
Provides-Extra: mysql
Requires-Dist: mysqlclient; extra == "mysql"
Dynamic: license-file
